MIPS32.v
`timescale 1ns / 1ps
//////////////////////////////////////////////////////////////////////////////////
// Company: 
// Engineer: 
// 
// Create Date: 06.09.2024 22:19:49
// Design Name: 
// Module Name: MIPS32
// Project Name: 
// Target Devices: 
// Tool Versions: 
// Description: 
// 
// Dependencies: 
// 
// Revision:
// Revision 0.01 - File Created
// Additional Comments:
// 
//////////////////////////////////////////////////////////////////////////////////


module pipe_MIPS32(clk1, clk2);
   
   input clk1, clk2;        //TWO Phase Clock
   reg [31:0] PC, IF_ID_IR,IF_ID_NPC;
   reg [31:0] ID_EX_IR, ID_EX_NPC, ID_EX_A, ID_EX_B, ID_EX_Imm;
   reg [2:0] ID_EX_type, EX_MEM_type, MEM_WB_type;
   reg [31:0] EX_MEM_IR, EX_MEM_ALUOut, EX_MEM_B;
   reg        EX_MEM_cond;                          //branch cond check
   reg [31:0] MEM_WB_IR, MEM_WB_ALUOut, MEM_WB_LMD;
   
   reg [31:0] Reg [0:31];       //Register bank 32x32
   reg [31:0] Mem [0:1023];     //1024x32 bit Memory
   
   parameter ADD=6'b000000, SUB=6'b000001, AND=6'b000010, OR=6'b000011, 
             SLT=6'b000100, MUL=6'b000101, HLT=6'b111111, LW=6'b001000,     //Store less than
             SW=6'b001001, ADDI=6'b001010, SUBI=6'b001011, SLTI=6'b001100,
             BNEQZ=6'b001101, BEQZ=6'b001110;   
   
   parameter RR_ALU=3'b000, RM_ALU=3'b001, LOAD=3'b010, STORE=3'b011, 
             BRANCH=3'b100, HALT=3'b101;
   reg HALTED;  //set after hlt instruction to terminate previous running inst(in WB stage)
   reg TAKEN_BRANCH;  //required to disable inst after branch
   
   always @(posedge clk1)          //IF stage
        if (HALTED==0)
        begin
            if(((EX_MEM_IR[31:26]==BEQZ) && (EX_MEM_cond==1)) ||    //cond=1 if A is 0
               ((EX_MEM_IR[31:26]==BNEQZ) && (EX_MEM_cond==0)))   //register A not zero
                begin
                 IF_ID_IR       <= #2   Mem[EX_MEM_ALUOut];
                 TAKEN_BRANCH   <= #2   1'b1;
                 IF_ID_NPC      <= #2   EX_MEM_ALUOut + 1;
                 PC             <= #2   EX_MEM_ALUOut + 1;
                end
            else 
            begin
                    IF_ID_IR    <= #2 Mem[PC];
                    IF_ID_NPC   <= #2 PC+1;
                    PC          <= #2 PC+1;
                end
         end
         
    always @(posedge clk2)          //ID stage
        if (HALTED==0)
        begin
            if (IF_ID_IR[25:21] == 5'b00000)    
            ID_EX_A<=0;
            else 
            ID_EX_A    <=  #2 Reg[IF_ID_IR[25:21]];    //rs(source register)
            
            if (IF_ID_IR[20:16] == 5'b00000)    ID_EX_B<=0;
            else ID_EX_B    <=  #2 Reg[IF_ID_IR[20:16]];     //rt
            
            ID_EX_NPC   <= #2   IF_ID_NPC;
            ID_EX_IR    <= #2   IF_ID_IR;
            ID_EX_Imm   <= #2   {{16{IF_ID_IR[15]}}, {IF_ID_IR[15:0]}}; //signed extension replicate
            
            case (IF_ID_IR[31:26])
                ADD,SUB,AND,OR,SLT,MUL: ID_EX_type    <= #2 RR_ALU;
                ADDI,SUBI,SLTI        : ID_EX_type    <= #2 RM_ALU;
                LW:                     ID_EX_type    <= #2 LOAD;
                SW:                     ID_EX_type    <= #2 STORE;
                BNEQZ,BEQZ:             ID_EX_type    <= #2 BRANCH;
                HLT:                    ID_EX_type    <= #2 HALT;
                default:                ID_EX_type    <= #2 HALT;       //INVALID OPCODE
             endcase
          end
          
       always @(posedge clk1)              //EX stage                  
          if(HALTED==0)
            begin
                EX_MEM_IR <= #2 ID_EX_IR;
                EX_MEM_type <= #2 ID_EX_type;
                TAKEN_BRANCH <= #2 0;
                
                case(ID_EX_type)
                RR_ALU: begin
                    case(ID_EX_IR[31:26]) 
                    ADD : EX_MEM_ALUOut <= #2 ID_EX_A + ID_EX_B;
                    SUB : EX_MEM_ALUOut <= #2  ID_EX_A - ID_EX_B;
                    OR : EX_MEM_ALUOut <= #2  ID_EX_A | ID_EX_B;
                    MUL : EX_MEM_ALUOut <= #2  ID_EX_A * ID_EX_B;
                    SLT : EX_MEM_ALUOut <= #2  ID_EX_A < ID_EX_B;
                    AND : EX_MEM_ALUOut <= #2  ID_EX_A & ID_EX_B;
                    default : EX_MEM_ALUOut <= #2  32'hx;
                 endcase
            end
                RM_ALU: begin
                case(ID_EX_IR[31:26])
                ADDI:   EX_MEM_ALUOut <= #2 ID_EX_A + ID_EX_Imm;
                SUBI:   EX_MEM_ALUOut <= #2  ID_EX_A - ID_EX_Imm;
                SLTI:   EX_MEM_ALUOut <= #2  ID_EX_A < ID_EX_Imm;
                default:  EX_MEM_ALUOut <=#2 32'hx;
                endcase
                end
                
                LOAD,STORE:
                    begin
                    EX_MEM_ALUOut <= #2 ID_EX_A + ID_EX_Imm;
                    EX_MEM_B      <= #2 ID_EX_B;
                    end
                BRANCH: begin
                    EX_MEM_ALUOut <= #2 ID_EX_NPC + ID_EX_Imm;
                    EX_MEM_cond   <= #2 (ID_EX_A==0);
                    end
                endcase
             end
        always @(posedge clk2)        //MEM stage
            if(HALTED==0) begin
                MEM_WB_type <= #2 EX_MEM_type;
                MEM_WB_IR   <= #2 EX_MEM_IR;
                
                    case (EX_MEM_type)
                    RR_ALU,RM_ALU:  MEM_WB_ALUOut <= #2 EX_MEM_ALUOut;
                    LOAD:           MEM_WB_LMD<= #2 Mem[EX_MEM_ALUOut];
                    STORE:
                        if (TAKEN_BRANCH==0)
                            Mem[EX_MEM_ALUOut] <= #2 EX_MEM_B;
                     endcase
                     end
           
          always @(posedge clk1)        //WB Stage
            begin if(TAKEN_BRANCH==0)
                case(MEM_WB_type)
                    RR_ALU: Reg[MEM_WB_IR[15:11]] <= #2 MEM_WB_ALUOut;  //rd
                    RM_ALU: Reg[MEM_WB_IR[20:16]] <= #2 MEM_WB_ALUOut;   //rt
                    LOAD:   Reg[MEM_WB_IR[20:16]] <= #2 MEM_WB_LMD;      //rt
                    HALT:   HALTED <= #2 1'b1;
                    endcase
                    end    
                 
endmodule

test3_mips.v
`timescale 1ns / 1p
//Factorial of a number
//////////////////////////////////////////////////////////////////////////////////
// Company: 
// Engineer: 
// 
// Create Date: 07.09.2024 22:58:57
// Design Name: 
// Module Name: test3_mips
// Project Name: 
// Target Devices: 
// Tool Versions: 
// Description: 
// 
// Dependencies: 
// 
// Revision:
// Revision 0.01 - File Created
// Additional Comments:
// 
//////////////////////////////////////////////////////////////////////////////////


module test3_mips32;
    reg clk1, clk2;
    integer k;
pipe_MIPS32 mips(clk1, clk2);
    initial
    begin
        clk1=0; clk2=0;
         repeat(50) begin
    #5 clk1=1; #5 clk1=0;
    #5 clk2=1; #5 clk2=0;
    end
end
initial
begin
    for(k=0; k<31; k=k+1)
        mips.Reg[k]=k;
        
        mips.Mem[0]=32'h280a00c8;       //ADDI R10, R0, 200
        mips.Mem[1]=32'h28020001;       //ADDI R2, R0, 1
        mips.Mem[2]=32'h0e94a000;       //OR R20, R20, R20--Dummy inst
        mips.Mem[3]=32'h21430000;       //LW R3, 0(R10)
        mips.Mem[4]=32'h0e94a000;       //OR R20, R20, R20--Dummy inst
        mips.Mem[5]=32'h14431000;       //LOOP: MUL R2, R2, R3
        mips.Mem[6]=32'h2c630001;       //SUBI R3, R3, 1
        mips.Mem[7]=32'h0e94a000;       
        mips.Mem[8]=32'h3460fffc;       //BNEQZ R3,Loop(ie -4 offset because PC is at mem9)
        mips.Mem[9]=32'h2542fffe;       //SW R2, -2(R10)
        mips.Mem[10]=32'hfc000000;      //HLT
        
        mips.Mem[200]=7;  //Facrorial of 7
        
        mips.PC=0;
        mips.HALTED=0;
        mips.TAKEN_BRANCH=0;
        
        #2000 $display("Mem[200] = %2d, Mem[198] = %6d", mips.Mem[200], mips.Mem[198]);
        
        end
initial 
begin
    $dumpfile("mips3.vcd");
    $dumpvars(0, test3_mips32);
    $monitor("R2: %4d", mips.Reg[2]);
    #3000 $finish;
    end
endmodule

mips3.vcd
$date
   Sun Sep  8 12:56:42 2024
$end
$version
  2018.3
$end
$timescale
  1ps
$end
$scope module test3_mips32 $end
$var reg 1 ! clk1 $end
$var reg 1 " clk2 $end
$var integer 32 # k $end
$scope module mips $end
$var wire 1 $ clk1 $end
$var wire 1 % clk2 $end
$var reg 32 & PC [31:0] $end
$var reg 32 ' IF_ID_IR [31:0] $end
$var reg 32 ( IF_ID_NPC [31:0] $end
$var reg 32 ) ID_EX_IR [31:0] $end
$var reg 32 * ID_EX_NPC [31:0] $end
$var reg 32 + ID_EX_A [31:0] $end
$var reg 32 , ID_EX_B [31:0] $end
$var reg 32 - ID_EX_Imm [31:0] $end
$var reg 3 . ID_EX_type [2:0] $end
$var reg 3 / EX_MEM_type [2:0] $end
$var reg 3 0 MEM_WB_type [2:0] $end
$var reg 32 1 EX_MEM_IR [31:0] $end
$var reg 32 2 EX_MEM_ALUOut [31:0] $end
$var reg 32 3 EX_MEM_B [31:0] $end
$var reg 1 4 EX_MEM_cond $end
$var reg 32 5 MEM_WB_IR [31:0] $end
$var reg 32 6 MEM_WB_ALUOut [31:0] $end
$var reg 32 7 MEM_WB_LMD [31:0] $end
$var reg 1 8 HALTED $end
$var reg 1 9 TAKEN_BRANCH $end
$var parameter 6 : ADD [5:0] $end
$var parameter 6 ; SUB [5:0] $end
$var parameter 6 < AND [5:0] $end
$var parameter 6 = OR [5:0] $end
$var parameter 6 > SLT [5:0] $end
$var parameter 6 ? MUL [5:0] $end
$var parameter 6 @ HLT [5:0] $end
$var parameter 6 A LW [5:0] $end
$var parameter 6 B SW [5:0] $end
$var parameter 6 C ADDI [5:0] $end
$var parameter 6 D SUBI [5:0] $end
$var parameter 6 E SLTI [5:0] $end
$var parameter 6 F BNEQZ [5:0] $end
$var parameter 6 G BEQZ [5:0] $end
$var parameter 3 H RR_ALU [2:0] $end
$var parameter 3 I RM_ALU [2:0] $end
$var parameter 3 J LOAD [2:0] $end
$var parameter 3 K STORE [2:0] $end
$var parameter 3 L BRANCH [2:0] $end
$var parameter 3 M HALT [2:0] $end
$upscope $end
$upscope $end
$enddefinitions $end
#0
$dumpvars
0!
0"
b11111 #
0$
0%
b0 &
bx '
bx (
bx )
bx *
bx +
bx ,
bx -
bx .
bx /
bx 0
bx 1
bx 2
bx 3
x4
bx 5
bx 6
bx 7
08
09
b0 :
b1 ;
b10 <
b11 =
b100 >
b101 ?
b111111 @
b1000 A
b1001 B
b1010 C
b1011 D
b1100 E
b1101 F
b1110 G
b0 H
b1 I
b10 J
b11 K
b100 L
b101 M
$end
#5000
1!
1$
#7000
b1 &
b101000000010100000000011001000 '
b1 (
#10000
0!
0$
#15000
1"
1%
b0 +
#17000
b101000000010100000000011001000 )
b1 *
b1010 ,
b11001000 -
b1 .
#20000
0"
0%
#25000
1!
1$
#27000
b10 &
b101000000000100000000000000001 '
b10 (
b1 /
b101000000010100000000011001000 1
b11001000 2
#30000
0!
0$
#35000
1"
1%
#37000
b101000000000100000000000000001 )
b10 *
b10 ,
b1 -
b1 0
b101000000010100000000011001000 5
b11001000 6
#40000
0"
0%
#45000
1!
1$
#47000
b11 &
b1110100101001010000000000000 '
b11 (
b101000000000100000000000000001 1
b1 2
#50000
0!
0$
#55000
1"
1%
#57000
b1110100101001010000000000000 )
b11 *
b10100 +
b10100 ,
b11111111111111111010000000000000 -
b0 .
b101000000000100000000000000001 5
b1 6
#60000
0"
0%
#65000
1!
1$
#67000
b100 &
b100001010000110000000000000000 '
b100 (
b0 /
b1110100101001010000000000000 1
b10100 2
#70000
0!
0$
#75000
1"
1%
#77000
b100001010000110000000000000000 )
b100 *
b11001000 +
b11 ,
b0 -
b10 .
b0 0
b1110100101001010000000000000 5
b10100 6
#80000
0"
0%
#85000
1!
1$
#87000
b101 &
b1110100101001010000000000000 '
b101 (
b10 /
b100001010000110000000000000000 1
b11001000 2
b11 3
#90000
0!
0$
#95000
1"
1%
#97000
b1110100101001010000000000000 )
b101 *
b10100 +
b10100 ,
b11111111111111111010000000000000 -
b0 .
b10 0
b100001010000110000000000000000 5
b111 7
#100000
0"
0%
#105000
1!
1$
#107000
b110 &
b10100010000110001000000000000 '
b110 (
b0 /
b1110100101001010000000000000 1
b10100 2
#110000
0!
0$
#115000
1"
1%
#117000
b10100010000110001000000000000 )
b110 *
b1 +
b111 ,
b1000000000000 -
b0 0
b1110100101001010000000000000 5
#120000
0"
0%
#125000
1!
1$
#127000
b111 &
b101100011000110000000000000001 '
b111 (
b10100010000110001000000000000 1
b111 2
#130000
0!
0$
#135000
1"
1%
#137000
b101100011000110000000000000001 )
b111 *
b111 +
b1 -
b1 .
b10100010000110001000000000000 5
b111 6
#140000
0"
0%
#145000
1!
1$
#147000
b1000 &
b1110100101001010000000000000 '
b1000 (
b1 /
b101100011000110000000000000001 1
b110 2
#150000
0!
0$
#155000
1"
1%
#157000
b1110100101001010000000000000 )
b1000 *
b10100 +
b10100 ,
b11111111111111111010000000000000 -
b0 .
b1 0
b101100011000110000000000000001 5
b110 6
#160000
0"
0%
#165000
1!
1$
#167000
b1001 &
b110100011000001111111111111100 '
b1001 (
b0 /
b1110100101001010000000000000 1
b10100 2
#170000
0!
0$
#175000
1"
1%
b0 ,
#177000
b110100011000001111111111111100 )
b1001 *
b110 +
b11111111111111111111111111111100 -
b100 .
b0 0
b1110100101001010000000000000 5
b10100 6
#180000
0"
0%
#185000
1!
1$
#187000
b1010 &
b100101010000101111111111111110 '
b1010 (
b100 /
b110100011000001111111111111100 1
b101 2
04
#190000
0!
0$
#195000
1"
1%
#197000
b100101010000101111111111111110 )
b1010 *
b11001000 +
b111 ,
b11111111111111111111111111111110 -
b11 .
b100 0
b110100011000001111111111111100 5
#200000
0"
0%
#205000
1!
1$
#207000
b110 &
b10100010000110001000000000000 '
b110 (
b11 /
b100101010000101111111111111110 1
b11000110 2
b111 3
09
#210000
0!
0$
#215000
1"
1%
#217000
b10100010000110001000000000000 )
b110 *
b111 +
b110 ,
b1000000000000 -
b0 .
b11 0
b100101010000101111111111111110 5
#220000
0"
0%
#225000
1!
1$
#227000
b111 &
b101100011000110000000000000001 '
b111 (
b0 /
b10100010000110001000000000000 1
b101010 2
#230000
0!
0$
#235000
1"
1%
#237000
b101100011000110000000000000001 )
b111 *
b110 +
b1 -
b1 .
b0 0
b10100010000110001000000000000 5
b101010 6
#240000
0"
0%
#245000
1!
1$
#247000
b1000 &
b1110100101001010000000000000 '
b1000 (
b1 /
b101100011000110000000000000001 1
b101 2
#250000
0!
0$
#255000
1"
1%
#257000
b1110100101001010000000000000 )
b1000 *
b10100 +
b10100 ,
b11111111111111111010000000000000 -
b0 .
b1 0
b101100011000110000000000000001 5
b101 6
#260000
0"
0%
#265000
1!
1$
#267000
b1001 &
b110100011000001111111111111100 '
b1001 (
b0 /
b1110100101001010000000000000 1
b10100 2
#270000
0!
0$
#275000
1"
1%
b0 ,
#277000
b110100011000001111111111111100 )
b1001 *
b101 +
b11111111111111111111111111111100 -
b100 .
b0 0
b1110100101001010000000000000 5
b10100 6
#280000
0"
0%
#285000
1!
1$
#287000
b1010 &
b100101010000101111111111111110 '
b1010 (
b100 /
b110100011000001111111111111100 1
b101 2
#290000
0!
0$
#295000
1"
1%
#297000
b100101010000101111111111111110 )
b1010 *
b11001000 +
b101010 ,
b11111111111111111111111111111110 -
b11 .
b100 0
b110100011000001111111111111100 5
#300000
0"
0%
#305000
1!
1$
#307000
b110 &
b10100010000110001000000000000 '
b110 (
b11 /
b100101010000101111111111111110 1
b11000110 2
b101010 3
09
#310000
0!
0$
#315000
1"
1%
#317000
b10100010000110001000000000000 )
b110 *
b101010 +
b101 ,
b1000000000000 -
b0 .
b11 0
b100101010000101111111111111110 5
#320000
0"
0%
#325000
1!
1$
#327000
b111 &
b101100011000110000000000000001 '
b111 (
b0 /
b10100010000110001000000000000 1
b11010010 2
#330000
0!
0$
#335000
1"
1%
#337000
b101100011000110000000000000001 )
b111 *
b101 +
b1 -
b1 .
b0 0
b10100010000110001000000000000 5
b11010010 6
#340000
0"
0%
#345000
1!
1$
#347000
b1000 &
b1110100101001010000000000000 '
b1000 (
b1 /
b101100011000110000000000000001 1
b100 2
#350000
0!
0$
#355000
1"
1%
#357000
b1110100101001010000000000000 )
b1000 *
b10100 +
b10100 ,
b11111111111111111010000000000000 -
b0 .
b1 0
b101100011000110000000000000001 5
b100 6
#360000
0"
0%
#365000
1!
1$
#367000
b1001 &
b110100011000001111111111111100 '
b1001 (
b0 /
b1110100101001010000000000000 1
b10100 2
#370000
0!
0$
#375000
1"
1%
b0 ,
#377000
b110100011000001111111111111100 )
b1001 *
b100 +
b11111111111111111111111111111100 -
b100 .
b0 0
b1110100101001010000000000000 5
b10100 6
#380000
0"
0%
#385000
1!
1$
#387000
b1010 &
b100101010000101111111111111110 '
b1010 (
b100 /
b110100011000001111111111111100 1
b101 2
#390000
0!
0$
#395000
1"
1%
#397000
b100101010000101111111111111110 )
b1010 *
b11001000 +
b11010010 ,
b11111111111111111111111111111110 -
b11 .
b100 0
b110100011000001111111111111100 5
#400000
0"
0%
#405000
1!
1$
#407000
b110 &
b10100010000110001000000000000 '
b110 (
b11 /
b100101010000101111111111111110 1
b11000110 2
b11010010 3
09
#410000
0!
0$
#415000
1"
1%
#417000
b10100010000110001000000000000 )
b110 *
b11010010 +
b100 ,
b1000000000000 -
b0 .
b11 0
b100101010000101111111111111110 5
#420000
0"
0%
#425000
1!
1$
#427000
b111 &
b101100011000110000000000000001 '
b111 (
b0 /
b10100010000110001000000000000 1
b1101001000 2
#430000
0!
0$
#435000
1"
1%
#437000
b101100011000110000000000000001 )
b111 *
b100 +
b1 -
b1 .
b0 0
b10100010000110001000000000000 5
b1101001000 6
#440000
0"
0%
#445000
1!
1$
#447000
b1000 &
b1110100101001010000000000000 '
b1000 (
b1 /
b101100011000110000000000000001 1
b11 2
#450000
0!
0$
#455000
1"
1%
#457000
b1110100101001010000000000000 )
b1000 *
b10100 +
b10100 ,
b11111111111111111010000000000000 -
b0 .
b1 0
b101100011000110000000000000001 5
b11 6
#460000
0"
0%
#465000
1!
1$
#467000
b1001 &
b110100011000001111111111111100 '
b1001 (
b0 /
b1110100101001010000000000000 1
b10100 2
#470000
0!
0$
#475000
1"
1%
b0 ,
#477000
b110100011000001111111111111100 )
b1001 *
b11 +
b11111111111111111111111111111100 -
b100 .
b0 0
b1110100101001010000000000000 5
b10100 6
#480000
0"
0%
#485000
1!
1$
#487000
b1010 &
b100101010000101111111111111110 '
b1010 (
b100 /
b110100011000001111111111111100 1
b101 2
#490000
0!
0$
#495000
1"
1%
#497000
b100101010000101111111111111110 )
b1010 *
b11001000 +
b1101001000 ,
b11111111111111111111111111111110 -
b11 .
b100 0
b110100011000001111111111111100 5
#500000
0"
0%
#505000
1!
1$
#507000
b110 &
b10100010000110001000000000000 '
b110 (
b11 /
b100101010000101111111111111110 1
b11000110 2
b1101001000 3
09
#510000
0!
0$
#515000
1"
1%
#517000
b10100010000110001000000000000 )
b110 *
b1101001000 +
b11 ,
b1000000000000 -
b0 .
b11 0
b100101010000101111111111111110 5
#520000
0"
0%
#525000
1!
1$
#527000
b111 &
b101100011000110000000000000001 '
b111 (
b0 /
b10100010000110001000000000000 1
b100111011000 2
#530000
0!
0$
#535000
1"
1%
#537000
b101100011000110000000000000001 )
b111 *
b11 +
b1 -
b1 .
b0 0
b10100010000110001000000000000 5
b100111011000 6
#540000
0"
0%
#545000
1!
1$
#547000
b1000 &
b1110100101001010000000000000 '
b1000 (
b1 /
b101100011000110000000000000001 1
b10 2
#550000
0!
0$
#555000
1"
1%
#557000
b1110100101001010000000000000 )
b1000 *
b10100 +
b10100 ,
b11111111111111111010000000000000 -
b0 .
b1 0
b101100011000110000000000000001 5
b10 6
#560000
0"
0%
#565000
1!
1$
#567000
b1001 &
b110100011000001111111111111100 '
b1001 (
b0 /
b1110100101001010000000000000 1
b10100 2
#570000
0!
0$
#575000
1"
1%
b0 ,
#577000
b110100011000001111111111111100 )
b1001 *
b10 +
b11111111111111111111111111111100 -
b100 .
b0 0
b1110100101001010000000000000 5
b10100 6
#580000
0"
0%
#585000
1!
1$
#587000
b1010 &
b100101010000101111111111111110 '
b1010 (
b100 /
b110100011000001111111111111100 1
b101 2
#590000
0!
0$
#595000
1"
1%
#597000
b100101010000101111111111111110 )
b1010 *
b11001000 +
b100111011000 ,
b11111111111111111111111111111110 -
b11 .
b100 0
b110100011000001111111111111100 5
#600000
0"
0%
#605000
1!
1$
#607000
b110 &
b10100010000110001000000000000 '
b110 (
b11 /
b100101010000101111111111111110 1
b11000110 2
b100111011000 3
09
#610000
0!
0$
#615000
1"
1%
#617000
b10100010000110001000000000000 )
b110 *
b100111011000 +
b10 ,
b1000000000000 -
b0 .
b11 0
b100101010000101111111111111110 5
#620000
0"
0%
#625000
1!
1$
#627000
b111 &
b101100011000110000000000000001 '
b111 (
b0 /
b10100010000110001000000000000 1
b1001110110000 2
#630000
0!
0$
#635000
1"
1%
#637000
b101100011000110000000000000001 )
b111 *
b10 +
b1 -
b1 .
b0 0
b10100010000110001000000000000 5
b1001110110000 6
#640000
0"
0%
#645000
1!
1$
#647000
b1000 &
b1110100101001010000000000000 '
b1000 (
b1 /
b101100011000110000000000000001 1
b1 2
#650000
0!
0$
#655000
1"
1%
#657000
b1110100101001010000000000000 )
b1000 *
b10100 +
b10100 ,
b11111111111111111010000000000000 -
b0 .
b1 0
b101100011000110000000000000001 5
b1 6
#660000
0"
0%
#665000
1!
1$
#667000
b1001 &
b110100011000001111111111111100 '
b1001 (
b0 /
b1110100101001010000000000000 1
b10100 2
#670000
0!
0$
#675000
1"
1%
b0 ,
#677000
b110100011000001111111111111100 )
b1001 *
b1 +
b11111111111111111111111111111100 -
b100 .
b0 0
b1110100101001010000000000000 5
b10100 6
#680000
0"
0%
#685000
1!
1$
#687000
b1010 &
b100101010000101111111111111110 '
b1010 (
b100 /
b110100011000001111111111111100 1
b101 2
#690000
0!
0$
#695000
1"
1%
#697000
b100101010000101111111111111110 )
b1010 *
b11001000 +
b1001110110000 ,
b11111111111111111111111111111110 -
b11 .
b100 0
b110100011000001111111111111100 5
#700000
0"
0%
#705000
1!
1$
#707000
b110 &
b10100010000110001000000000000 '
b110 (
b11 /
b100101010000101111111111111110 1
b11000110 2
b1001110110000 3
09
#710000
0!
0$
#715000
1"
1%
#717000
b10100010000110001000000000000 )
b110 *
b1001110110000 +
b1 ,
b1000000000000 -
b0 .
b11 0
b100101010000101111111111111110 5
#720000
0"
0%
#725000
1!
1$
#727000
b111 &
b101100011000110000000000000001 '
b111 (
b0 /
b10100010000110001000000000000 1
b1001110110000 2
#730000
0!
0$
#735000
1"
1%
#737000
b101100011000110000000000000001 )
b111 *
b1 +
b1 -
b1 .
b0 0
b10100010000110001000000000000 5
b1001110110000 6
#740000
0"
0%
#745000
1!
1$
#747000
b1000 &
b1110100101001010000000000000 '
b1000 (
b1 /
b101100011000110000000000000001 1
b0 2
#750000
0!
0$
#755000
1"
1%
#757000
b1110100101001010000000000000 )
b1000 *
b10100 +
b10100 ,
b11111111111111111010000000000000 -
b0 .
b1 0
b101100011000110000000000000001 5
b0 6
#760000
0"
0%
#765000
1!
1$
#767000
b1001 &
b110100011000001111111111111100 '
b1001 (
b0 /
b1110100101001010000000000000 1
b10100 2
#770000
0!
0$
#775000
1"
1%
b0 ,
#777000
b110100011000001111111111111100 )
b1001 *
b0 +
b11111111111111111111111111111100 -
b100 .
b0 0
b1110100101001010000000000000 5
b10100 6
#780000
0"
0%
#785000
1!
1$
#787000
b1010 &
b100101010000101111111111111110 '
b1010 (
b100 /
b110100011000001111111111111100 1
b101 2
14
#790000
0!
0$
#795000
1"
1%
#797000
b100101010000101111111111111110 )
b1010 *
b11001000 +
b1001110110000 ,
b11111111111111111111111111111110 -
b11 .
b100 0
b110100011000001111111111111100 5
#800000
0"
0%
#805000
1!
1$
#807000
b1011 &
b11111100000000000000000000000000 '
b1011 (
b11 /
b100101010000101111111111111110 1
b11000110 2
#810000
0!
0$
#815000
1"
1%
b0 +
b0 ,
#817000
b11111100000000000000000000000000 )
b1011 *
b0 -
b101 .
b11 0
b100101010000101111111111111110 5
#820000
0"
0%
#825000
1!
1$
#827000
b1100 &
bx '
b1100 (
b101 /
b11111100000000000000000000000000 1
#830000
0!
0$
#835000
1"
1%
#837000
bx )
b1100 *
bx +
bx ,
bx -
b101 0
b11111100000000000000000000000000 5
#840000
0"
0%
#845000
1!
1$
#847000
b1101 &
b1101 (
bx 1
18
